decon/__init__.py
decon-0.0.1.dist-info/LICENSE
decon-0.0.1.dist-info/METADATA
decon-0.0.1.dist-info/WHEEL
decon-0.0.1.dist-info/top_level.txt
decon-0.0.1.dist-info/RECORD
